hiutils/__init__.py
hiutils/annotations.py
hiutils/hiutils.py
hiutils/ontology.py
hiutils/stats.py
hiutils-0.2.2.dist-info/METADATA
hiutils-0.2.2.dist-info/WHEEL
hiutils-0.2.2.dist-info/top_level.txt
hiutils-0.2.2.dist-info/RECORD
