Metadata-Version: 2.1
Name: hiutils
Version: 0.2.2
Summary: Utilities for health informatics
Home-page: https://github.com/dbeanm/hiutils
Author: Dan Bean
Author-email: daniel.bean@kcl.ac.uk
License: UNKNOWN
Platform: UNKNOWN
Classifier: Programming Language :: Python :: 3
Classifier: License :: OSI Approved :: GNU Lesser General Public License v3 (LGPLv3)
Classifier: Operating System :: OS Independent
Requires-Python: >=3.6
Requires-Dist: numpy (~=1.21.4)
Requires-Dist: pandas (~=1.3.4)
Requires-Dist: scipy (~=1.7.2)
Requires-Dist: statsmodels (~=0.13.0)
